flask_mobility/__init__.py
flask_mobility/decorators.py
flask_mobility/mobility.py
Flask_Mobility-2.0.0.dist-info/LICENSE
Flask_Mobility-2.0.0.dist-info/METADATA
Flask_Mobility-2.0.0.dist-info/WHEEL
Flask_Mobility-2.0.0.dist-info/top_level.txt
Flask_Mobility-2.0.0.dist-info/RECORD
